aio_geojson_usgs_earthquakes/__init__.py
aio_geojson_usgs_earthquakes/consts.py
aio_geojson_usgs_earthquakes/feed.py
aio_geojson_usgs_earthquakes/feed_entry.py
aio_geojson_usgs_earthquakes/feed_manager.py
aio_geojson_usgs_earthquakes-0.4.dist-info/LICENSE
aio_geojson_usgs_earthquakes-0.4.dist-info/METADATA
aio_geojson_usgs_earthquakes-0.4.dist-info/WHEEL
aio_geojson_usgs_earthquakes-0.4.dist-info/top_level.txt
aio_geojson_usgs_earthquakes-0.4.dist-info/RECORD
