Metadata-Version: 2.1
Name: aio_geojson_usgs_earthquakes
Version: 0.4
Summary: An async GeoJSON client library for the U.S. Geological Survey Earthquake Hazards Program.
Author-email: Malte Franken <coding@subspace.de>
License: Apache License
Project-URL: Repository, https://github.com/exxamalte/python-aio-geojson-usgs-earthquakes
Project-URL: Issues, https://github.com/exxamalte/python-aio-geojson-usgs-earthquakes/issues
Project-URL: Changelog, https://github.com/exxamalte/python-aio-geojson-usgs-earthquakes/blob/main/CHANGELOG.md
Keywords: homeassistant,geojson,usgs,earthquakes
Classifier: Programming Language :: Python :: 3.9
Classifier: Programming Language :: Python :: 3.10
Classifier: Programming Language :: Python :: 3.11
Classifier: Programming Language :: Python :: 3.12
Classifier: License :: OSI Approved :: Apache Software License
Classifier: Operating System :: OS Independent
Classifier: Development Status :: 5 - Production/Stable
Requires-Python: >=3.9
License-File: LICENSE
Requires-Dist: aio-geojson-client>=0.21
Requires-Dist: aiohttp<4,>=3.7.4
Requires-Dist: pytz>=2019.01
Provides-Extra: tests
Requires-Dist: pytest-asyncio; extra == "tests"
Requires-Dist: pytest-timeout; extra == "tests"
Requires-Dist: pytest-xdist; extra == "tests"
Requires-Dist: pytest-cov; extra == "tests"
Requires-Dist: coverage; extra == "tests"
Requires-Dist: mock; extra == "tests"
Requires-Dist: aioresponses; extra == "tests"
